{
  "id": "019cf612-df04-7d43-b38b-2201b493ef8e",
  "content": "w();\n        let mut all_success = true;\n\n        for entry in &snapshot {\n            let model_type = match entry.model_type.as_str() {\n                \"embedding\" => ModelType::Embedding,\n                \"chat\" => ModelType::Chat,\n                _ => {\n                    results.push(ModelReloadResult {\n                        name: entry.name.clone(),\n                        model_type: entry.model_type.clone(),\n                        success: false,\n                        error: format!(\"Unknown model_type: '{}'\", entry.model_type),\n                        actual_device: String::new(),\n                        actual_backend: String::new(),\n                    });\n                    all_success = false;\n                    continue;\n                }\n            };\n\n            // Use embedding_backend override for embedding models when set.\n            let effective_backend = if model_type == ModelType::Embedding && !req.embedding_backend.is_empty() {\n                &req.embedding_backend\n            } else {\n                &req.backend\n            };\n\n            let resolved = {\n                let gpu = self.gpu.read().map_err(|e| Status::internal(format!(\"GPU lock poisoned: {e}\")))?;\n                match backend::resolve_backend(&req.device, effective_backend, model_type, &gpu) {\n                    Ok(r) => r,\n                    Err(e) => {\n                        results.push(ModelReloadResult {\n                            name: entry.name.clone(),\n                            model_type: entry.model_type.clone(),\n                            success: false,\n                            error: e,\n                            actual_device: String::new(),\n                            actual_backend: String::new(),\n                        });\n                        all_success = false;\n                        continue;\n                    }\n                }\n            };\n\n            let kv_cache_type = match resolve_kv_quant(&req.kv_quant) {\n                Ok(t) => t,",
  "source_version": "crates/corvia-inference/src/model_manager.rs",
  "scope_id": "corvia",
  "workstream": "kernel",
  "recorded_at": "2026-03-16T09:55:57.828948626Z",
  "valid_from": "2026-03-16T09:55:57.828948626Z",
  "valid_to": null,
  "superseded_by": null,
  "embedding": [
    0.025245534,
    0.01606771,
    -0.17135328,
    -0.013840202,
    0.0815321,
    -0.021289686,
    0.029888127,
    -0.0218837,
    -0.022196528,
    -0.017081305,
    -0.03166191,
    0.035518296,
    0.07730309,
    0.035070784,
    -0.03307006,
    0.01435103,
    0.004015147,
    -0.055506233,
    0.0012859437,
    -0.015650928,
    -0.047140993,
    -0.06669809,
    0.039201077,
    0.013448444,
    0.020758498,
    0.020669222,
    0.02318974,
    0.060410466,
    -0.007179163,
    0.009901297,
    0.087470375,
    -0.016760636,
    0.038945846,
    -0.08004463,
    -0.0235098,
    -0.039009262,
    0.006768976,
    -0.014374528,
    0.046246935,
    -0.008717993,
    0.022640731,
    0.031668514,
    0.049715772,
    0.01652527,
    0.0148345595,
    0.0041943872,
    0.07579786,
    -0.028239086,
    0.077802464,
    -0.03826631,
    0.06296338,
    -0.0089099305,
    0.036597285,
    -0.043754723,
    0.11072667,
    -0.026038548,
    -0.026992297,
    0.028299907,
    0.055270366,
    -0.036948185,
    -0.006202457,
    0.06678556,
    -0.03479891,
    0.045302827,
    0.029826492,
    -0.024083493,
    -0.058957122,
    0.029985523,
    -0.014089328,
    -0.044994894,
    0.03486278,
    -0.0015465195,
    0.021568127,
    -0.02688349,
    0.02165739,
    -0.011359328,
    -0.015244212,
    -0.02647574,
    -0.011852157,
    0.03201131,
    -0.01895056,
    0.019983947,
    0.052993905,
    0.024278264,
    0.048412465,
    -0.016470222,
    -0.06495989,
    0.014223509,
    -0.07814278,
    0.03337899,
    0.000809403,
    0.009438982,
    0.023995608,
    0.039736953,
    -0.035973597,
    0.012032252,
    -0.02930156,
    0.025349034,
    -0.07286847,
    0.0072302963,
    -0.0009239526,
    -0.046999812,
    -0.0069687143,
    -0.03132202,
    -0.019668397,
    0.082373396,
    -0.009240038,
    0.015170676,
    0.020938229,
    -0.0023421438,
    -0.009751486,
    0.03265727,
    -0.017046621,
    -0.035094492,
    -0.04090445,
    0.01369005,
    0.018671026,
    -0.0202242,
    0.0005655377,
    0.0058357627,
    0.0055992357,
    -0.0027097038,
    -0.06460254,
    -0.015755322,
    0.014155372,
    -0.009161151,
    -0.010096171,
    -0.02584898,
    0.03822051,
    0.014454639,
    0.04397982,
    -0.049225852,
    -0.04857392,
    0.04394267,
    0.060173508,
    0.050859895,
    -0.008793908,
    0.0063110027,
    0.009593985,
    0.029300299,
    -0.050450776,
    -0.015392308,
    0.0013194553,
    -0.035187267,
    -0.030815784,
    -0.06635548,
    0.06351458,
    -0.027547045,
    -0.027434917,
    0.0052825836,
    -0.04644897,
    0.062251933,
    -0.054358706,
    0.015372433,
    0.053379614,
    -0.026565667,
    0.007489185,
    0.006873764,
    0.05713165,
    -0.03481359,
    0.052122425,
    -0.04873367,
    -0.03330319,
    0.02135099,
    0.01994821,
    -0.050841738,
    0.021907844,
    0.03746974,
    0.047133703,
    0.046793863,
    -0.03486463,
    -0.046264272,
    0.0076649375,
    -0.059661057,
    0.011869791,
    0.039300777,
    0.030752974,
    -0.025282893,
    -0.0015589118,
    -0.017656224,
    0.04645782,
    -0.015775058,
    0.021836432,
    -0.03923213,
    -0.01951129,
    -0.0024570974,
    0.0051726843,
    -0.033959262,
    0.008312963,
    -0.0011422987,
    0.027118264,
    0.007765086,
    -0.06497225,
    -0.028940136,
    -0.016514186,
    -0.027775876,
    0.0602568,
    -0.024541628,
    0.002284228,
    -0.029492896,
    -0.03172577,
    0.023656305,
    0.0019136225,
    0.040435303,
    -0.043095097,
    -0.0035640693,
    -0.037831683,
    0.038088687,
    -0.013794371,
    0.050961316,
    0.027287602,
    0.032915946,
    0.0017305043,
    0.032212798,
    0.027407395,
    -0.020309698,
    0.032786485,
    -0.016227746,
    -0.079921976,
    -0.021161964,
    0.0066796327,
    -0.012798644,
    0.027903171,
    -0.0136890225,
    0.024051094,
    0.03229524,
    -0.026098074,
    0.04722805,
    -0.0241035,
    -0.018612027,
    -0.017582161,
    -0.048582233,
    -0.010567123,
    -0.02482253,
    0.000401272,
    0.017499365,
    0.00721834,
    0.075694606,
    -0.024478624,
    0.019769417,
    0.027352914,
    0.050027903,
    0.0006364301,
    -0.02209396,
    -0.025597584,
    0.007643859,
    -0.018765518,
    -0.036109474,
    0.011842465,
    0.045903716,
    -0.03671819,
    0.016842976,
    0.04873392,
    -0.022490198,
    0.0308413,
    -0.011785424,
    0.00092010736,
    -0.05811275,
    -0.002140082,
    -0.0023113398,
    0.046662826,
    0.01979031,
    0.0025913669,
    -0.006939454,
    -0.028392756,
    -0.027278641,
    0.006668219,
    -0.01406428,
    -0.022610666,
    0.0039071343,
    -0.0066082836,
    0.023764238,
    -0.0069284127,
    0.06964247,
    0.04946523,
    0.02022756,
    0.010221115,
    -0.0075367894,
    0.0052462276,
    -0.014858385,
    -0.05747976,
    -0.051211916,
    -0.0019060011,
    -0.032320566,
    -0.02920868,
    -0.017151205,
    0.031934157,
    -0.020268505,
    -0.0048401495,
    0.012308774,
    0.02447853,
    0.044494547,
    0.022045918,
    0.019665169,
    0.022417845,
    0.049768317,
    0.032915633,
    0.0057969964,
    0.010138154,
    -0.009623481,
    0.0027296324,
    0.037133206,
    0.023780676,
    -0.011040888,
    -0.015710317,
    -0.027799701,
    0.03572662,
    -0.030003393,
    -0.010474174,
    0.0035622166,
    -0.033655163,
    -0.00004195574,
    -0.05267084,
    -0.025625587,
    -0.021117538,
    0.02125006,
    0.015120054,
    -0.016383246,
    0.020237805,
    -0.024114354,
    -0.034332328,
    -0.024106873,
    0.027901748,
    -0.0171416,
    -0.017374739,
    0.062779635,
    0.010421745,
    -0.04027145,
    -0.0010294421,
    0.004830095,
    0.03354313,
    0.053191792,
    0.05364412,
    -0.014478863,
    -0.014643866,
    0.020001855,
    -0.0779594,
    0.019770933,
    -0.009388469,
    0.02522271,
    0.0348915,
    -0.016117567,
    0.047113806,
    -0.013130151,
    0.014081915,
    0.017636472,
    -0.024548505,
    -0.01950486,
    0.10488131,
    0.0048481226,
    -0.024225915,
    0.020105882,
    -0.004915585,
    0.012276313,
    -0.03988718,
    -0.019315477,
    -0.016150922,
    -0.002631023,
    -0.019031703,
    0.008569491,
    0.04160462,
    -0.0303252,
    0.010343767,
    -0.045525946,
    0.009706728,
    0.0050911214,
    0.06481302,
    0.038448017,
    0.04340967,
    0.0054798373,
    0.0048140166,
    0.0060613975,
    -0.017446352,
    0.050567567,
    0.046863414,
    0.0042021973,
    -0.036173165,
    -0.0034798232,
    -0.031752534,
    0.024663689,
    0.01246788,
    -0.03885123,
    -0.016152954,
    -0.00681564,
    0.011023316,
    0.014638732,
    0.001500754,
    -0.05005171,
    0.010591722,
    0.039568525,
    -0.00904871,
    0.024461245,
    -0.05627953,
    0.017483922,
    0.0040296367,
    -0.073259145,
    0.033071436,
    -0.036486167,
    -0.028498104,
    -0.02185882,
    -0.0120168645,
    -0.026107809,
    0.033886716,
    -0.0011282236,
    0.035142552,
    -0.034453288,
    -0.017901758,
    0.031742577,
    0.03354749,
    0.009716051,
    0.018577637,
    0.05961922,
    0.019829825,
    -0.09055603,
    0.04778707,
    -0.030820515,
    0.061748836,
    0.037748344,
    -0.05321074,
    -0.029728848,
    0.0008434654,
    0.057878524,
    0.034755103,
    0.01720247,
    0.08994509,
    0.019797344,
    0.004570159,
    0.03947422,
    0.024662761,
    -0.11469299,
    0.001541326,
    0.02316194,
    0.020057064,
    -0.020999398,
    -0.0050019,
    -0.034735322,
    0.003382851,
    0.029383454,
    -0.014628721,
    0.055400196,
    0.056793887,
    -0.027263043,
    -0.020711476,
    0.023368925,
    0.06581162,
    0.09626273,
    0.050743744,
    -0.021709982,
    -0.047944423,
    0.026109561,
    -0.061924852,
    0.009500656,
    0.02633207,
    0.0096912775,
    0.084432445,
    -0.056324165,
    -0.0077478406,
    0.04973283,
    0.013554688,
    0.050148085,
    -0.0033590905,
    0.039004035,
    -0.00059039716,
    0.043056984,
    0.027091185,
    -0.037542306,
    -0.010717871,
    0.00039341635,
    0.0060893944,
    0.022740303,
    -0.033318795,
    -0.0015967267,
    0.034572978,
    0.0131549705,
    0.010092,
    0.051186096,
    -0.00814895,
    0.033365324,
    0.0074104173,
    0.05604013,
    -0.009311732,
    -0.024738919,
    -0.050511286,
    -0.06943836,
    0.037230466,
    0.06753339,
    0.0080226585,
    0.038788278,
    0.031439945,
    0.0052019428,
    0.043096807,
    0.019167092,
    0.019617356,
    0.0075904294,
    -0.035080966,
    -0.030941075,
    0.00012513515,
    0.037118584,
    -0.0034300773,
    0.036255073,
    -0.005153181,
    -0.013084243,
    0.010436672,
    0.0025464096,
    0.025792524,
    -0.0019186735,
    -0.019410398,
    -0.04657348,
    -0.052592263,
    -0.043882936,
    0.0023111918,
    0.015249986,
    0.0011698757,
    0.032857064,
    0.037341602,
    -0.05788868,
    -0.016964396,
    0.026910335,
    -0.05654322,
    -0.026344664,
    0.020459425,
    -0.07628251,
    -0.04607184,
    -0.023101378,
    -0.08477311,
    0.059487723,
    0.021916091,
    -0.08088619,
    0.0046725837,
    -0.030050931,
    0.013882624,
    0.0066835717,
    -0.025010131,
    0.047014713,
    0.043807615,
    -0.015872728,
    -0.019557873,
    0.013410554,
    0.0030265977,
    0.019004261,
    0.005852557,
    0.027825918,
    -0.018893205,
    -0.052018773,
    0.0073954877,
    0.0011388417,
    -0.012852051,
    0.057718255,
    0.031821944,
    -0.08069909,
    0.018826922,
    -0.035608806,
    -0.010809441,
    -0.04900757,
    -0.018078921,
    -0.027166354,
    -0.030756222,
    -0.08093554,
    -0.017892715,
    -0.0350169,
    -0.02909621,
    0.023094654,
    0.021560563,
    -0.0057563134,
    -0.0039655305,
    0.010875131,
    -0.007853698,
    -0.015186694,
    0.026275927,
    -0.029914925,
    0.018912338,
    -0.047135785,
    0.0251304,
    -0.02245358,
    -0.004541412,
    0.029281558,
    0.012600234,
    0.02906855,
    -0.031297963,
    -0.04536122,
    0.015272723,
    -0.021491261,
    0.026539294,
    0.019307604,
    0.022151206,
    0.010140522,
    0.008496942,
    -0.026885182,
    0.0155488085,
    0.011121818,
    -0.0149422735,
    -0.002837981,
    0.026243955,
    0.0035351072,
    0.0123603055,
    0.0297699,
    -0.021330165,
    -0.02452664,
    -0.05286678,
    -0.045851514,
    0.014631341,
    0.020457167,
    0.02842995,
    -0.09369977,
    -0.019941306,
    0.054548997,
    -0.04854434,
    -0.007101563,
    0.022632087,
    0.02938692,
    -0.031019298,
    -0.019061496,
    0.0025306528,
    -0.015303532,
    0.043106858,
    -0.056366175,
    0.046388198,
    0.0026996285,
    -0.031414088,
    -0.02498647,
    -0.032856062,
    -0.045470357,
    0.04026647,
    -0.024198215,
    0.023548864,
    0.0013551532,
    -0.04837116,
    -0.009644854,
    0.040855814,
    0.012067254,
    -0.054383077,
    -0.010892039,
    -0.10742968,
    -0.024075683,
    -0.0589786,
    0.026323613,
    -0.022392727,
    0.030356819,
    0.010238401,
    0.06270741,
    0.05847834,
    0.014383987,
    -0.017818866,
    0.008786407,
    -0.009297565,
    -0.025725504,
    0.044957414,
    0.04930071,
    0.0047327653,
    0.019464295,
    0.12243334,
    0.1331255,
    -0.015331056,
    -0.016936673,
    -0.00652045,
    0.023617707,
    -0.0030251925,
    0.006167195,
    -0.09192383,
    -0.0076659387,
    -0.028371753,
    -0.0018535046,
    -0.04010485,
    -0.03823589,
    0.089424565,
    -0.010887332,
    -0.032138858,
    -0.000093713235,
    -0.019472502,
    -0.06636117,
    -0.034461256,
    -0.015220776,
    -0.0020423855,
    0.010074945,
    0.04718228,
    -0.04782353,
    0.027883442,
    0.056548834,
    0.0020050367,
    -0.04723946,
    0.004463268,
    0.013995169,
    0.027096467,
    0.034276914,
    0.014762006,
    -0.063985094,
    -0.03380382,
    -0.023572244,
    -0.08133856,
    0.00066661404,
    -0.026680637,
    -0.021524593,
    0.047927354,
    0.007277556,
    -0.06976602,
    0.0693644,
    -0.04171711,
    -0.033502847,
    -0.020007232,
    0.036694102,
    -0.02527051,
    0.015692059,
    0.051490765,
    0.0049400697,
    -0.034815468,
    -0.007870285,
    0.030016694,
    -0.013057371,
    0.009980007,
    -0.04287096,
    -0.046735175,
    0.031505026,
    -0.030553699,
    0.020520441,
    0.029235182,
    -0.0013494361,
    -0.044827092,
    -0.053610932,
    0.01655124,
    0.011534258,
    0.0039094305,
    0.012684088,
    -0.034000635,
    0.032286983,
    0.054411195,
    -0.05459128,
    0.013196043,
    -0.0110108415,
    -0.036054157,
    -0.013149303,
    -0.05845546,
    -0.05624561,
    -0.024592794,
    0.052970167,
    0.0039801816,
    0.013314418,
    -0.026438642,
    -0.022208367,
    -0.06284136,
    -0.021150578,
    -0.075082876,
    -0.017673269,
    -0.001677153,
    0.012659068,
    -0.058055058,
    -0.013731135,
    -0.023651244,
    0.047137026,
    -0.006255319,
    0.009273327,
    0.021277538,
    -0.021294916,
    -0.034927122,
    0.0145126,
    0.011899241,
    -0.005317575,
    0.0054465337,
    0.032890808,
    0.110109404,
    0.049740583,
    0.017060181,
    -0.04447547,
    -0.014080277,
    0.0374402,
    -0.023649244,
    -0.020898994,
    -0.022515709,
    -0.006117009
  ],
  "metadata": {
    "source_file": "crates/corvia-inference/src/model_manager.rs",
    "language": "rs",
    "chunk_type": "impl_item",
    "start_line": 255,
    "end_line": 295,
    "content_role": "code",
    "source_origin": "repo:corvia"
  },
  "agent_id": null,
  "session_id": null,
  "entry_status": "Merged"
}