{
  "id": "019cf5fd-6141-7e93-a4dc-26a24ea939aa",
  "content": "tring[]> = {\n      agent: [\"corvia.agent.\", \"corvia.session.\"],\n      entry: [\"corvia.entry.\"],\n      merge: [\"corvia.merge.\"],\n      storage: [\"corvia.store.\"],\n      rag: [\"corvia.rag.\"],\n      gc: [\"corvia.gc.\"],\n      inference: [\"corvia.entry.embed\"],\n    };\n    const prefixes = spanPrefixes[module] ?? [];\n    return prefixes.some((p) => name.startsWith(p));\n  });\n}\n\nconst latencyColor = (ms: number): string => {\n  if (ms < 50) return \"var(--mint)\";\n  if (ms < 150) return \"var(--peach)\";\n  return \"var(--coral)\";\n};\n\nexport const TracesView: FunctionComponent<TracesViewProps> = ({ traces }) => {\n  const [selected, setSelected] = useState<string | null>(null);\n\n  const spans = traces?.spans ?? {};\n  const events = traces?.recent_events ?? [];\n\n  const selectedModule = MODULES.find((m) => m.name === selected);\n  const selectedSpans = selected ? moduleSpans(selected, spans) : [];\n  const selectedEvents = selected\n    ? events.filter((e) => e.module === selected)\n    : [];\n\n  return (\n    <div class=\"traces-view\">\n      <div class=\"topology-graph\">\n        {MODULES.map((mod) => {\n          const modSpans = moduleSpans(mod.name, spans);\n          const totalCount = modSpans.reduce((s, [, st]) => s + st.count, 0);\n\n          return (\n            <div\n              key={mod.name}\n              class={`tnode ${selected === mod.name ? \"selected\" : \"\"}`}\n              style={{ left: mod.x, top: mod.y }}\n              onClick={() => setSelected(selected === mod.name ? null : mod.name)}\n            >\n              <div class=\"tnode-header\">\n                <span class=\"tnode-emoji\">{mod.emoji}</span>\n                <span class=\"tnode-label\">{mod.label}</span>\n              </div>\n              <div class=\"tnode-count\" style={{ color: `var(--${mod.color})` }}>\n                {totalCount > 0 ? totalCount.toLocaleString() : \"—\"}\n              </div>\n            </div>\n          );\n        })}\n      </div>\n\n      {selectedModule && (\n        <div class=\"traces-detail\">\n          <div class=\"detail-header\">",
  "source_version": "docs/rfcs/2026-03-11-dashboard-ui-standalone.md",
  "scope_id": "corvia",
  "workstream": "kernel",
  "recorded_at": "2026-03-16T09:32:29.377690578Z",
  "valid_from": "2026-03-16T09:32:29.377690578Z",
  "valid_to": null,
  "superseded_by": null,
  "embedding": [
    0.031693444,
    0.0012126603,
    -0.1280735,
    -0.14117858,
    0.047645118,
    -0.069488816,
    0.056567956,
    -0.010017988,
    0.052256137,
    -0.049636528,
    -0.05531148,
    0.035357554,
    0.11451894,
    -0.013048632,
    -0.021095494,
    -0.035302207,
    -0.03453814,
    0.026695998,
    0.008036318,
    0.014483045,
    0.01390393,
    -0.03332537,
    0.054879963,
    -0.017204272,
    0.09704633,
    0.03492386,
    -0.004498307,
    0.0116947545,
    0.009499195,
    0.0049104337,
    0.031141197,
    0.021948623,
    -0.0119939,
    -0.032922473,
    -0.06967125,
    -0.044382937,
    0.038039222,
    0.0032523444,
    -0.054466646,
    -0.015283931,
    -0.0053130854,
    -0.025002774,
    0.015984038,
    -0.030312732,
    0.026123801,
    -0.028286966,
    0.1427044,
    0.0028941755,
    -0.029683363,
    -0.052367337,
    0.008244885,
    -0.014540001,
    -0.0047107176,
    -0.021500258,
    0.04744297,
    0.053331345,
    -0.010524885,
    -0.0254902,
    0.062516764,
    -0.039767012,
    0.07232574,
    -0.0073101595,
    -0.05347319,
    0.09163929,
    0.026676496,
    -0.021786755,
    -0.035922073,
    0.039552074,
    0.033970598,
    0.0034997184,
    0.02553829,
    0.015174576,
    0.02683589,
    -0.02262874,
    -0.03565852,
    0.07198817,
    -0.013635472,
    0.01998965,
    -0.04772319,
    0.08112893,
    -0.011843704,
    -0.026722612,
    -0.0089213075,
    0.00041157083,
    0.03541424,
    -0.049767025,
    -0.011852491,
    -0.027919738,
    -0.0047953166,
    0.047137935,
    0.035262305,
    -0.0005153292,
    0.05554065,
    0.017563846,
    -0.055204965,
    0.04615663,
    -0.040078223,
    0.013696896,
    0.002099367,
    -0.033715125,
    -0.018802004,
    -0.007467119,
    0.0032868637,
    -0.013795875,
    -0.005873124,
    0.05654487,
    0.0023160842,
    -0.0068457075,
    -0.02500363,
    -0.027946277,
    -0.014760901,
    -0.021492014,
    -0.047556676,
    -0.030758694,
    0.01975563,
    0.010715898,
    0.010218772,
    -0.022536721,
    0.024021482,
    -0.003764534,
    -0.02547245,
    -0.052873697,
    -0.023838121,
    0.06493839,
    0.019981697,
    -0.0146272695,
    0.03323438,
    -0.012795431,
    0.022573987,
    -0.05178705,
    -0.04255009,
    0.02403597,
    -0.0053070886,
    0.049634557,
    0.051606297,
    0.033141658,
    -0.047898784,
    -0.013322467,
    0.029306129,
    0.020883154,
    -0.02992987,
    0.009299086,
    0.0010857059,
    -0.03406019,
    -0.02971206,
    -0.07103813,
    0.029013233,
    0.0161239,
    -0.05759592,
    -0.015554077,
    -0.012321898,
    0.009984376,
    0.019929081,
    0.029446838,
    0.038126852,
    -0.04674532,
    0.012707244,
    -0.015863115,
    0.0027709438,
    0.0134433005,
    0.015889585,
    -0.035505693,
    0.008846554,
    0.024863932,
    -0.005911607,
    -0.028030459,
    0.06254406,
    0.010636138,
    0.014591912,
    0.00029639676,
    -0.03313344,
    -0.022334607,
    -0.047181927,
    -0.029955463,
    0.006639868,
    0.0006543121,
    0.017525716,
    -0.06979826,
    0.040297825,
    -0.03677162,
    0.059429742,
    -0.026030872,
    -0.006767038,
    0.051089354,
    0.039234564,
    -0.022651663,
    -0.021506106,
    -0.044170436,
    0.016240837,
    -0.04085742,
    -0.009434578,
    -0.00054897583,
    -0.018557616,
    -0.03154381,
    -0.051190805,
    -0.034311738,
    0.043498524,
    -0.040774506,
    -0.004998807,
    -0.03524731,
    -0.024546463,
    -0.002468662,
    -0.041675866,
    0.05311933,
    -0.050360244,
    -0.0018632238,
    -0.026502337,
    0.042668957,
    -0.042897336,
    0.019377748,
    0.057620138,
    0.010434462,
    0.017559506,
    0.03918687,
    -0.027206047,
    -0.014133185,
    0.04147394,
    -0.006347438,
    0.0059216116,
    0.035787657,
    0.021875417,
    -0.020626348,
    0.053166658,
    -0.012394606,
    0.031824842,
    0.007774671,
    -0.014495233,
    0.019945884,
    -0.025286417,
    -0.002703564,
    -0.039113943,
    -0.014589359,
    0.058284763,
    0.013278371,
    0.043817993,
    0.018541533,
    0.023133444,
    0.048032217,
    0.005742507,
    0.023215136,
    0.010164446,
    -0.0034408027,
    -0.005515499,
    -0.014260217,
    -0.029204661,
    -0.0151874,
    0.012891537,
    0.014703639,
    -0.00409867,
    0.038918145,
    0.0070689092,
    0.037571836,
    0.044324692,
    -0.02754207,
    0.043829344,
    -0.029068585,
    -0.00048879394,
    -0.026026161,
    0.047110785,
    0.036761705,
    0.03529897,
    0.008606177,
    0.025264045,
    -0.01998548,
    0.009030091,
    -0.07714445,
    0.019345485,
    -0.05692444,
    -0.050856013,
    -0.021344235,
    -0.049658474,
    0.0140083395,
    0.033407267,
    -0.01278198,
    0.0038924632,
    0.033464603,
    0.027266325,
    -0.04186352,
    -0.028215945,
    -0.0410251,
    -0.041185766,
    -0.028087627,
    -0.035555698,
    0.023643505,
    0.0062241745,
    0.0017799179,
    -0.016454473,
    0.046943843,
    0.051033504,
    0.02693091,
    0.034133505,
    0.03910732,
    0.0028332302,
    0.0029869839,
    0.048365273,
    -0.005431464,
    -0.0021164713,
    -0.01836165,
    0.037781563,
    -0.012208627,
    -0.017947407,
    0.069505565,
    0.03181861,
    0.043813232,
    -0.026985187,
    -0.00029512175,
    0.015454324,
    -0.003125583,
    0.04776478,
    -0.0032817856,
    -0.052336298,
    -0.020775976,
    0.004793806,
    0.030067904,
    -0.029137736,
    0.02110726,
    -0.026111068,
    0.02943443,
    0.04404479,
    0.036671553,
    -0.036020577,
    -0.011628794,
    0.024575382,
    -0.04489257,
    0.01228026,
    0.06875634,
    -0.035652664,
    0.007557799,
    0.032621782,
    -0.00987894,
    0.042122778,
    0.018286541,
    0.005008386,
    -0.017209508,
    -0.0483277,
    -0.01294898,
    -0.00089896977,
    -0.013752391,
    0.014893254,
    0.049656574,
    0.0041294903,
    -0.061063003,
    0.0060894033,
    -0.0474239,
    -0.015601836,
    0.028629927,
    -0.047054745,
    -0.054242797,
    0.0781812,
    0.021156006,
    -0.029817011,
    0.0029527687,
    -0.05274798,
    -0.030119622,
    -0.010917143,
    0.009545098,
    0.013794942,
    0.0031614297,
    -0.0011221174,
    0.009436001,
    0.023980362,
    -0.024183668,
    -0.026344292,
    -0.048658248,
    0.035499267,
    0.014991915,
    0.048152957,
    0.046500422,
    0.08286199,
    -0.010503749,
    -0.020400325,
    -0.012355618,
    0.0013855799,
    0.043391235,
    -0.018499289,
    -0.0026127305,
    -0.072665766,
    0.017841674,
    -0.013391569,
    -0.0027675,
    0.011566794,
    -0.0064787227,
    0.036931925,
    -0.020187598,
    0.0025815722,
    0.014761767,
    0.051657237,
    -0.024799863,
    -0.014322979,
    0.030742604,
    -0.023380276,
    0.003571959,
    -0.08889567,
    0.002289815,
    0.054919414,
    -0.0049675,
    0.0018116438,
    0.047624305,
    -0.01853502,
    -0.0039472296,
    -0.05470182,
    -0.048481517,
    0.022972774,
    -0.05724532,
    -0.01887438,
    0.02084352,
    -0.032988735,
    0.017632162,
    0.037254907,
    -0.01304343,
    0.045513257,
    0.020052219,
    0.06257125,
    -0.018521223,
    0.060743455,
    -0.01840653,
    0.094650865,
    0.03703874,
    -0.054688975,
    -0.0020670034,
    -0.049432736,
    0.030935511,
    0.008958474,
    0.004591662,
    0.024365697,
    0.028169291,
    -0.0031425722,
    0.049422428,
    -0.055322196,
    -0.041878153,
    -0.009716011,
    0.027447838,
    0.045067452,
    -0.015864741,
    -0.048741214,
    -0.0036082896,
    0.0011946047,
    -0.004699614,
    0.005866954,
    0.05156324,
    -0.0013407692,
    -0.06902073,
    -0.004541923,
    -0.07968981,
    0.05645458,
    0.04694019,
    0.0043863268,
    -0.035936512,
    -0.03173579,
    0.026886689,
    -0.024540091,
    0.00057723647,
    -0.010322913,
    0.007455519,
    0.055643387,
    -0.041031573,
    -0.0010842234,
    0.0025964184,
    -0.026834015,
    -0.0035233365,
    -0.0053956327,
    0.06399875,
    -0.1045428,
    -0.020317724,
    0.0157016,
    -0.033140756,
    0.006247139,
    0.010673728,
    0.100034654,
    0.05115565,
    0.0039219656,
    -0.02010864,
    0.009332843,
    -0.033922702,
    0.019702995,
    0.009021556,
    0.026087511,
    0.031739496,
    0.02559727,
    0.0935743,
    0.023262063,
    -0.01495193,
    -0.041111458,
    -0.014560977,
    -0.023520354,
    0.053502176,
    -0.008772282,
    -0.036536712,
    0.014907151,
    -0.026206061,
    0.030087719,
    -0.002326801,
    0.035913426,
    0.015653143,
    -0.004891735,
    -0.02965235,
    0.007901308,
    0.023237314,
    0.026679128,
    -0.017757425,
    0.020340994,
    0.043342225,
    -0.07011408,
    0.008890598,
    0.00013992617,
    -0.009083696,
    -0.009473413,
    -0.044067316,
    -0.039512355,
    0.025302697,
    0.018105218,
    0.016464556,
    0.001405829,
    0.046277523,
    0.010844265,
    -0.08246665,
    -0.03372685,
    0.0049918625,
    -0.043980237,
    0.022448972,
    0.0041858465,
    0.004777122,
    -0.032270383,
    -0.09984745,
    -0.083523616,
    0.05053564,
    0.012907314,
    -0.07251458,
    -0.0018579484,
    -0.020013146,
    0.011552585,
    0.01366533,
    -0.021526026,
    0.005490225,
    0.028074272,
    -0.04195876,
    -0.06992974,
    0.03576108,
    -0.004348297,
    -0.004493556,
    0.021573793,
    0.032116618,
    -0.002843324,
    -0.035184212,
    0.014429748,
    -0.017124215,
    0.010856964,
    0.019965163,
    0.018859014,
    -0.02470625,
    0.03934516,
    -0.030206319,
    0.022463424,
    -0.07893089,
    0.022138814,
    0.005299986,
    -0.060510773,
    -0.036399126,
    -0.033469334,
    0.04648662,
    -0.017367141,
    -0.03573938,
    0.062042344,
    0.00959528,
    -0.026567772,
    0.005467396,
    -0.021323038,
    0.029867718,
    0.0009982692,
    0.03413163,
    0.06502118,
    -0.066824116,
    -0.012110519,
    0.026896132,
    0.011163002,
    -0.007040944,
    -0.03540484,
    -0.0054729893,
    -0.027729673,
    -0.076412104,
    0.045977462,
    -0.03500097,
    0.0037607197,
    0.061345708,
    0.0048761526,
    0.0028635012,
    -0.049155958,
    -0.07194283,
    0.0025455663,
    -0.013948489,
    0.026990416,
    0.019595016,
    0.026950693,
    0.025905695,
    0.038627084,
    -0.006205025,
    -0.0017987142,
    0.016701914,
    0.013114172,
    0.015119634,
    0.025662638,
    0.010977555,
    0.08337726,
    -0.036081385,
    -0.004906593,
    0.049764123,
    -0.030827591,
    0.0047039306,
    -0.00007254883,
    -0.04271503,
    0.046601288,
    -0.025783269,
    -0.017535776,
    0.013379791,
    0.027015455,
    0.012586733,
    0.008135341,
    -0.009790348,
    -0.018559158,
    -0.024306176,
    0.0018153001,
    -0.04061157,
    0.057601437,
    0.00026053182,
    0.0338634,
    -0.008211427,
    -0.06086836,
    -0.03565428,
    0.003563756,
    0.013419497,
    -0.039360937,
    0.017540902,
    -0.081463955,
    -0.015648887,
    -0.07408417,
    0.09397403,
    -0.04544225,
    0.03170684,
    0.026197786,
    0.057316948,
    0.017916413,
    0.01748945,
    -0.04157058,
    0.0010822729,
    0.0059911907,
    -0.04009358,
    0.032620568,
    0.026024697,
    0.015154593,
    0.00034231605,
    0.09249858,
    0.097525485,
    0.08261029,
    0.029344052,
    -0.0054050647,
    -0.022873513,
    0.026329698,
    -0.022269042,
    -0.06209634,
    -0.006878666,
    -0.07956147,
    0.02850682,
    -0.028256964,
    0.026234478,
    0.0382913,
    -0.027603785,
    -0.0066340677,
    0.0037414772,
    -0.05731675,
    -0.08075047,
    0.012107713,
    -0.0066907294,
    -0.025972156,
    0.04405806,
    0.028204404,
    0.0060965335,
    0.032294925,
    0.027699556,
    0.029507777,
    -0.0033639309,
    0.009910225,
    -0.050609086,
    0.01878394,
    0.026914788,
    0.03526965,
    -0.059346646,
    0.008340915,
    -0.03230887,
    -0.034880444,
    -0.033170413,
    -0.026854005,
    0.026230838,
    0.017982159,
    0.036676817,
    -0.0013524997,
    0.03602166,
    0.06007519,
    0.00152347,
    0.015553063,
    0.07064741,
    0.014636434,
    0.034353353,
    0.04573442,
    -0.04136794,
    -0.013105996,
    -0.011745455,
    -0.006781845,
    -0.0034866072,
    -0.010194793,
    -0.0126897255,
    -0.011282634,
    0.03964438,
    -0.019151064,
    0.033812724,
    0.0003625898,
    0.047143724,
    -0.011683433,
    -0.015965894,
    -0.015811473,
    0.013534169,
    -0.07682582,
    -0.017061194,
    -0.02628135,
    -0.0017808698,
    0.03521378,
    -0.048582178,
    0.038430206,
    0.040531747,
    -0.040018436,
    0.016728908,
    -0.0021292062,
    -0.017627036,
    -0.051394552,
    0.030539796,
    -0.03895279,
    -0.008531068,
    -0.038332578,
    -0.08002725,
    -0.037113722,
    -0.010799714,
    -0.034762617,
    -0.0017544817,
    -0.002332727,
    0.009569026,
    -0.03615269,
    -0.00812196,
    -0.042324204,
    0.03981302,
    -0.0018299045,
    -0.028679049,
    -0.0064592566,
    0.00008810225,
    -0.049803242,
    0.017723635,
    -0.04009425,
    0.040277652,
    0.032360516,
    0.014132827,
    0.087118335,
    0.004391732,
    0.00059505994,
    0.016474223,
    0.03584117,
    0.018180665,
    -0.049256638,
    -0.023122806,
    -0.029906405,
    -0.030683586
  ],
  "metadata": {
    "source_file": "docs/rfcs/2026-03-11-dashboard-ui-standalone.md",
    "language": "markdown",
    "chunk_type": "heading_section",
    "start_line": 986,
    "end_line": 1038,
    "content_role": "design",
    "source_origin": "repo:corvia"
  },
  "agent_id": null,
  "session_id": null,
  "entry_status": "Merged"
}