{
  "id": "019d440d-f831-7562-9884-aa10c66ca8b4",
  "content": "t_validate_and_build_valid_config() {\n        use crate::lite_store::LiteStore;\n        use crate::traits::{InferenceEngine, QueryableStore};\n        use corvia_common::config::PipelineConfig;\n\n        struct MockEngine;\n        #[async_trait::async_trait]\n        impl InferenceEngine for MockEngine {\n            async fn embed(&self, _: &str) -> corvia_common::errors::Result<Vec<f32>> {\n                Ok(vec![1.0, 0.0, 0.0])\n            }\n            async fn embed_batch(&self, texts: &[String]) -> corvia_common::errors::Result<Vec<Vec<f32>>> {\n                Ok(texts.iter().map(|_| vec![1.0, 0.0, 0.0]).collect())\n            }\n            fn dimensions(&self) -> usize { 3 }\n        }\n\n        let dir = tempfile::tempdir().unwrap();\n        let store = Arc::new(LiteStore::open(dir.path(), 3).unwrap());\n        let engine = Arc::new(MockEngine) as Arc<dyn InferenceEngine>;\n\n        let config = PipelineConfig::default();\n        let deps = ComponentDeps {\n            store: Some(store as Arc<dyn QueryableStore>),\n            engine: Some(engine),\n            graph: None,\n            fts: None,\n            rrf_k: 60,\n            channels: Default::default(),\n            searcher_timeout_ms: 5000,\n        };\n\n        let result = PipelineRegistry::validate_and_build(&config, &deps, None, 0.3);\n        assert!(result.is_ok(), \"valid config should build successfully\");\n    }\n\n    #[test]\n    fn test_validate_and_build_all_unknown_searchers() {\n        use corvia_common::config::PipelineConfig;\n\n        let mut config = PipelineConfig::default();\n        config.searchers = vec![\"nonexistent1\".into(), \"nonexistent2\".into()];\n\n        let deps = ComponentDeps {\n            store: None,\n            engine: None,\n            graph: None,\n            fts: None,\n            rrf_k: 60,\n            channels: Default::default(),\n            searcher_timeout_ms: 5000,\n        };",
  "source_version": "crates/corvia-kernel/src/pipeline/registry.rs",
  "scope_id": "corvia",
  "workstream": "kernel",
  "recorded_at": "2026-03-31T13:20:59.441322197Z",
  "valid_from": "2026-03-31T13:20:59.441322197Z",
  "valid_to": null,
  "superseded_by": null,
  "metadata": {
    "source_file": "crates/corvia-kernel/src/pipeline/registry.rs",
    "language": "rs",
    "chunk_type": "mod_item",
    "start_line": 365,
    "end_line": 409,
    "content_role": "code",
    "source_origin": "repo:corvia"
  },
  "agent_id": null,
  "session_id": null,
  "entry_status": "Merged",
  "memory_type": "structural",
  "confidence": null,
  "last_accessed": null,
  "access_count": 0,
  "tier": "hot",
  "tier_changed_at": null,
  "retention_score": null,
  "pin": null
}