{
  "id": "019d440d-f837-7c71-ac7d-03ad65f466a9",
  "content": "────────\n    let mut inbound_edge_map: HashMap<uuid::Uuid, u32> = HashMap::new();\n\n    for entry in &scope_entries {\n        report.entries_scanned += 1;\n\n        // Skip pinned entries\n        if entry.pin.is_some() {\n            continue;\n        }\n        // Skip Forgotten (terminal)\n        if entry.tier == Tier::Forgotten {\n            continue;\n        }\n\n        // Resolve policy for this entry's memory type\n        let policy = forgetting.resolve_policy(entry.memory_type, scope_override);\n        if !policy.enabled {\n            continue;\n        }\n\n        report.entries_scored += 1;\n\n        // Compute retention params (clamp to non-negative for clock skew safety)\n        let days_since_creation =\n            (now - entry.recorded_at).num_seconds().max(0) as f64 / 86400.0;\n        let days_since_access = entry\n            .last_accessed\n            .map(|la| (now - la).num_seconds().max(0) as f64 / 86400.0);\n        let inbound_edges = graph\n            .edges(&entry.id, EdgeDirection::Incoming)\n            .await\n            .map(|e| e.len() as u32)\n            .unwrap_or(0);\n\n        // Cache for budget phase\n        inbound_edge_map.insert(entry.id, inbound_edges);\n\n        let params = RetentionParams {\n            memory_type: entry.memory_type,\n            days_since_creation,",
  "source_version": "crates/corvia-kernel/src/gc_worker.rs",
  "scope_id": "corvia",
  "workstream": "kernel",
  "recorded_at": "2026-03-31T13:20:59.447160626Z",
  "valid_from": "2026-03-31T13:20:59.447160626Z",
  "valid_to": null,
  "superseded_by": null,
  "metadata": {
    "source_file": "crates/corvia-kernel/src/gc_worker.rs",
    "language": "rs",
    "chunk_type": "function_item",
    "start_line": 321,
    "end_line": 352,
    "content_role": "code",
    "source_origin": "repo:corvia"
  },
  "agent_id": null,
  "session_id": null,
  "entry_status": "Merged",
  "memory_type": "structural",
  "confidence": null,
  "last_accessed": null,
  "access_count": 0,
  "tier": "hot",
  "tier_changed_at": null,
  "retention_score": null,
  "pin": null
}