{
  "id": "019d440d-f847-7f61-b488-6cadeb094a8a",
  "content": "# Build adapters\n# Put on PATH\n\n# Verify discovery\n./target/debug/corvia adapters list\n```\n\nExpected output includes both basic and git adapters.\n\n**Step 4: Test ingest with discovered adapter**\n\n```bash\n\n# Create a test directory\nmkdir -p /tmp/corvia-test-ingest\necho \"fn main() {}\" > /tmp/corvia-test-ingest/test.rs\n",
  "source_version": "docs/rfcs/2026-03-03-adapter-plugin-system.md",
  "scope_id": "corvia",
  "workstream": "kernel",
  "recorded_at": "2026-03-31T13:20:59.463105849Z",
  "valid_from": "2026-03-31T13:20:59.463105849Z",
  "valid_to": null,
  "superseded_by": null,
  "metadata": {
    "source_file": "docs/rfcs/2026-03-03-adapter-plugin-system.md",
    "language": "markdown",
    "chunk_type": "heading_section",
    "start_line": 2625,
    "end_line": 2637,
    "content_role": "design",
    "source_origin": "repo:corvia"
  },
  "agent_id": null,
  "session_id": null,
  "entry_status": "Merged",
  "memory_type": "decisional",
  "confidence": null,
  "last_accessed": null,
  "access_count": 0,
  "tier": "hot",
  "tier_changed_at": null,
  "retention_score": null,
  "pin": null
}