{
  "id": "019d286a-f2d8-78b2-92cd-5a5f26daaf98",
  "content": "ic filesystem adapter binary (D78)\n\nMinimal adapter that walks directories, reads text files, and streams\nJSONL. Supports both CLI mode (ingest <path>) and session mode (JSONL\nover stdin/stdout). No custom chunking — kernel defaults handle it.\"\n```\n\n---\n\n## Task 8: Move corvia-adapter-git into Monorepo\n\nMove the external `corvia-adapter-git` repo into `crates/corvia-adapter-git/` and add a JSONL `main.rs` wrapper.\n\n**Files:**\n- Create: `crates/corvia-adapter-git/` (copy from `/root/corvia-adapter-git/src/`)\n- Modify: `crates/corvia-adapter-git/Cargo.toml` (workspace deps, add [[bin]])\n- Create: `crates/corvia-adapter-git/src/main.rs` (JSONL wrapper)\n- Modify: `Cargo.toml` (add to workspace members)\n\n**Step 1: Copy source files**\n\n```bash\nmkdir -p crates/corvia-adapter-git/src\ncp /root/corvia-adapter-git/src/lib.rs crates/corvia-adapter-git/src/\ncp /root/corvia-adapter-git/src/git.rs crates/corvia-adapter-git/src/\ncp /root/corvia-adapter-git/src/ast_chunker.rs crates/corvia-adapter-git/src/\ncp /root/corvia-adapter-git/src/treesitter.rs crates/corvia-adapter-git/src/\n```\n\n**Step 2: Create workspace-aware Cargo.toml**\n\nCreate `crates/corvia-adapter-git/Cargo.toml`:\n\n```toml\n[package]\nname = \"corvia-adapter-git\"\nversion.workspace = true\nedition.workspace = true\nlicense.workspace = true\nrepository.workspace = true\nhomepage.workspace = true\nrust-version.workspace = true\ndescription = \"Git repository and source code ingestion adapter for Corvia using tree-sitter\"\nkeywords = [\"ai-agents\", \"tree-sitter\", \"code-analysis\", \"ingestion\", \"knowledge-graph\"]\ncategories = [\"development-tools\", \"parser-implementations\"]\n\n[lib]\nname = \"corvia_adapter_git\"\npath = \"src/lib.rs\"\n\n[[bin]]\nname = \"corvia-adapter-git\"\npath = \"src/main.rs\"\n\n[dependencies]\ncorvia-common.workspace = true\ncorvia-kernel.workspace = true\nserde.workspace = true\nserde_json.workspace = true\nasync-trait = \"0.1\"\ntree-sitter = \"0.26\"\ntree-sitter-language = \"0.1\"\ntree-sitter-rust = \"0.24\"\ntree-sitter-javascript = \"0.25\"\ntree-sitter-typescript = \"0.23\"\ntree-sitter-python = \"0.25\"\ngit2 = \"0.20\"\ntokio = { version = \"1\", features = [\"full\"] }\ntracing = \"0.1\"\nwalkdir = \"2\"\n\n[dev-dependencies]\ntempfile = \"3\"\n```\n\n**Step 3: Create JSONL main.rs wrapper**",
  "source_version": "docs/rfcs/2026-03-03-adapter-plugin-system.md",
  "scope_id": "corvia",
  "workstream": "kernel",
  "recorded_at": "2026-03-26T04:33:10.872504630Z",
  "valid_from": "2026-03-26T04:33:10.872504630Z",
  "valid_to": null,
  "superseded_by": null,
  "embedding": [
    -0.010892613,
    0.05633675,
    -0.14364275,
    -0.07281967,
    0.030410616,
    -0.12205583,
    -0.012971264,
    0.04053942,
    -0.053988673,
    -0.03285366,
    -0.052211013,
    0.017489469,
    0.06995802,
    0.030994399,
    0.018924959,
    -0.025008513,
    -0.0122613795,
    -0.009926198,
    0.014101822,
    -0.00031548995,
    0.017251644,
    -0.008270369,
    -0.0077354372,
    -0.033534165,
    0.09865623,
    0.018375954,
    -0.00859608,
    0.06363069,
    -0.03505701,
    0.06873719,
    0.07140196,
    -0.012386763,
    0.005076672,
    -0.03367676,
    -0.040851586,
    -0.05365301,
    0.0029280763,
    -0.024533274,
    -0.025087308,
    0.020026533,
    -0.048302006,
    -0.04259846,
    0.009480852,
    -0.058820594,
    0.03684689,
    -0.041970145,
    0.08947669,
    -0.03010882,
    0.044415765,
    -0.083168924,
    -0.015312063,
    0.0029881552,
    -0.06065501,
    -0.0018121431,
    0.060639564,
    0.032444008,
    -0.02551708,
    0.002017798,
    -0.006819295,
    -0.03352071,
    0.0060357144,
    0.057656545,
    -0.0016317359,
    0.06556491,
    -0.0048772125,
    0.02298709,
    -0.0021274893,
    0.01924867,
    -0.0031740558,
    -0.004809936,
    0.10113408,
    -0.015548223,
    0.024138877,
    0.007160833,
    -0.005241835,
    0.006097739,
    -0.032724876,
    -0.012638455,
    -0.01896569,
    0.008082559,
    0.027155377,
    -0.015025728,
    0.029507894,
    0.019259574,
    0.061011635,
    0.020324951,
    0.008447072,
    0.033560056,
    0.031059306,
    0.071890905,
    -0.0051758876,
    -0.014950299,
    0.06571992,
    0.0065328903,
    -0.051263627,
    0.0030054285,
    -0.01831613,
    0.015691545,
    -0.026566757,
    -0.015164746,
    -0.015327862,
    -0.010343798,
    0.0020645452,
    0.008172537,
    -0.026922088,
    0.06505465,
    0.012549861,
    0.0043313364,
    0.041960657,
    -0.02217781,
    -0.04346202,
    0.03342081,
    -0.0022314338,
    -0.09054539,
    0.056564514,
    -0.019245414,
    0.00061191403,
    -0.016619116,
    0.036975157,
    0.051327076,
    -0.011862162,
    -0.037960272,
    -0.02025204,
    0.04491117,
    0.012775268,
    -0.036426608,
    -0.028009854,
    -0.03604404,
    0.017213192,
    -0.027715625,
    -0.030088969,
    -0.02675377,
    -0.028908053,
    0.009822191,
    0.08357066,
    0.028396312,
    -0.0682305,
    -0.030421231,
    0.03601295,
    -0.019661514,
    -0.016367085,
    0.019409861,
    0.015712267,
    0.03698212,
    0.017434891,
    -0.049473852,
    -0.000027266413,
    0.005396497,
    -0.0350132,
    0.014456002,
    -0.026562171,
    0.022513004,
    0.004944675,
    0.047085516,
    0.040092688,
    -0.010321554,
    0.010036927,
    0.0009910838,
    0.05418252,
    0.02836421,
    0.017438991,
    0.020358492,
    -0.04353168,
    0.05171069,
    -0.011354358,
    -0.065839976,
    0.06597042,
    0.06372994,
    0.046421885,
    0.030936154,
    -0.017946776,
    -0.057352033,
    -0.059586074,
    -0.017299421,
    -0.022256488,
    0.01354296,
    0.033509333,
    -0.01991693,
    0.024290636,
    -0.01222972,
    0.027169487,
    -0.031196129,
    0.009962033,
    0.036062315,
    -0.016870627,
    -0.0147253135,
    0.010461943,
    -0.07096036,
    -0.0020169788,
    -0.027318351,
    0.015569289,
    0.010293775,
    -0.038022526,
    -0.007741526,
    -0.077433,
    -0.05139335,
    0.03054155,
    -0.060430042,
    0.016778294,
    -0.0647988,
    -0.026209202,
    -0.023679215,
    -0.040420018,
    0.04151241,
    0.011047358,
    0.01657994,
    -0.03290967,
    0.005863178,
    -0.0022101891,
    0.029807335,
    0.09703004,
    0.022691952,
    -0.0361177,
    -0.014005653,
    0.009886249,
    0.0030061495,
    -0.0014113015,
    -0.032933712,
    0.0032258593,
    0.013485422,
    0.014308414,
    -0.026952254,
    0.052644067,
    -0.026910322,
    0.03545852,
    -0.041120235,
    -0.0145846205,
    -0.009375103,
    -0.015856622,
    0.03454003,
    -0.021262102,
    -0.016097331,
    0.034539685,
    -0.00045522567,
    0.025264602,
    -0.00096679415,
    -0.006140528,
    0.06972096,
    -0.020576885,
    0.010203614,
    0.015191083,
    -0.0021522865,
    -0.013517535,
    -0.018653573,
    -0.045455724,
    0.01641506,
    0.037517633,
    -0.04500391,
    -0.018917162,
    0.04227321,
    -0.027401863,
    0.04842294,
    0.009872723,
    0.016193284,
    0.04868884,
    0.013021121,
    -0.0027616513,
    -0.024656696,
    -0.011932756,
    -0.026479637,
    0.035586607,
    -0.07806038,
    0.0037539925,
    -0.02304642,
    -0.0067591374,
    -0.04715037,
    -0.009381545,
    0.0119467,
    0.01933309,
    -0.008521514,
    -0.0345529,
    0.029638635,
    0.011646406,
    0.006776354,
    -0.008217076,
    0.028625583,
    0.0023385705,
    0.0073301913,
    -0.055427816,
    0.035089582,
    -0.04702351,
    -0.030442098,
    -0.04228783,
    -0.02831282,
    -0.02769839,
    0.031779215,
    0.02504988,
    0.022423029,
    -0.006958257,
    -0.0027614112,
    0.02786397,
    -0.001277806,
    -0.02306367,
    0.013228572,
    0.03031189,
    0.04953844,
    0.021748845,
    0.01657117,
    -0.031385977,
    0.02220194,
    0.029719748,
    0.03983624,
    0.052272547,
    0.056851618,
    -0.03397686,
    -0.001762848,
    -0.016920183,
    -0.010696842,
    -0.0074828905,
    0.06447413,
    -0.009070521,
    -0.017123526,
    -0.055331167,
    0.039342284,
    0.008946907,
    0.022275696,
    0.021918388,
    -0.015620304,
    0.048038155,
    0.012486978,
    0.019043108,
    -0.0058475984,
    -0.01405363,
    -0.032661844,
    -0.007832511,
    0.04494685,
    -0.0084702205,
    0.08286904,
    0.03622273,
    -0.0069420226,
    0.016655464,
    0.010531064,
    0.0026151373,
    -0.018811632,
    -0.0633916,
    -0.014176959,
    -0.008178795,
    -0.026294203,
    0.014466264,
    0.037007708,
    -0.0039246874,
    -0.0060327086,
    0.012165678,
    -0.016535219,
    -0.047407325,
    -0.009395023,
    -0.019847138,
    0.021292351,
    0.059119906,
    0.043911003,
    -0.041380428,
    0.0051929746,
    -0.021331,
    -0.010172442,
    -0.016343627,
    -0.0026170718,
    0.024976341,
    0.044511013,
    0.059838757,
    0.014773133,
    0.064054884,
    -0.014263998,
    0.010743071,
    0.0032746787,
    0.040080406,
    -0.017711246,
    0.025845414,
    -0.03302148,
    0.00835594,
    0.010682071,
    -0.002751466,
    0.010367527,
    0.017118523,
    0.036159653,
    0.013380972,
    -0.016414303,
    -0.05500444,
    0.015877767,
    -0.0109933,
    0.031836882,
    -0.012572719,
    -0.060355756,
    0.04903861,
    0.0049839476,
    0.03272842,
    -0.016934214,
    0.030226115,
    -0.0027492505,
    0.04667813,
    0.08840055,
    -0.033076577,
    -0.023628647,
    0.0027096344,
    -0.02512061,
    -0.011614519,
    0.029742187,
    0.019773487,
    0.056754515,
    -0.051562835,
    0.0055897436,
    -0.052662913,
    -0.06780629,
    0.022824803,
    -0.011997784,
    -0.010249825,
    -0.0272004,
    -0.013032674,
    -0.0054187435,
    0.071562245,
    -0.0004046944,
    0.020228766,
    0.012873056,
    0.0076358276,
    -0.035568055,
    0.075995125,
    -0.04907078,
    0.079993516,
    0.045733668,
    -0.018373042,
    -0.00800929,
    0.017411644,
    0.03387152,
    -0.017295405,
    0.0066587,
    0.0028269833,
    0.029781334,
    -0.00499277,
    0.046766564,
    0.042667836,
    -0.072086886,
    0.008090363,
    -0.013212412,
    0.0626038,
    -0.016557751,
    -0.02372389,
    -0.014957913,
    0.004835652,
    0.009330398,
    -0.010806343,
    0.04068507,
    0.026863735,
    -0.036028165,
    -0.024609454,
    -0.02690483,
    0.041000087,
    0.06952984,
    0.04541431,
    -0.035231806,
    -0.032929424,
    0.020326218,
    0.03585456,
    0.017476946,
    0.04127774,
    0.011674316,
    0.10500777,
    -0.03163738,
    0.07420574,
    -0.023290971,
    0.04058113,
    0.017050557,
    -0.047391344,
    0.01849199,
    -0.04982444,
    0.01571779,
    -0.008380126,
    0.004571772,
    -0.03734745,
    -0.065271676,
    0.08429147,
    0.06770423,
    0.0027689175,
    -0.0055114054,
    -0.010279553,
    0.0069505437,
    0.02697225,
    0.0010889745,
    -0.0035016253,
    0.036629345,
    -0.016872942,
    0.03616802,
    -0.024965463,
    -0.023839079,
    -0.0195856,
    -0.054071765,
    0.0021519412,
    0.085548215,
    0.036833648,
    0.02206693,
    -0.009213178,
    -0.007666693,
    0.017446086,
    0.030909838,
    0.015759299,
    0.03710226,
    0.013227788,
    0.021352518,
    -0.06416431,
    -0.039221656,
    0.021040399,
    0.040752947,
    0.024217103,
    0.016738182,
    -0.0065437322,
    0.019358505,
    -0.0014559551,
    -0.044018935,
    0.00022405865,
    0.015319298,
    -0.08338544,
    -0.013905202,
    -0.032684997,
    0.023799723,
    -0.020012567,
    0.02290653,
    0.050995253,
    -0.068958335,
    0.0030956166,
    -0.03367653,
    -0.034660373,
    -0.0026576766,
    -0.019937912,
    -0.024720103,
    -0.0051205982,
    -0.014265756,
    -0.09301404,
    0.05695341,
    0.030679723,
    -0.057360444,
    0.0539103,
    -0.03224183,
    0.011952564,
    0.00031212159,
    -0.0037617336,
    0.005811245,
    -0.03818959,
    0.017545978,
    -0.085511506,
    0.068379946,
    0.002679432,
    -0.019188495,
    0.006163517,
    -0.016710555,
    -0.010613633,
    -0.01628594,
    -0.05038355,
    -0.067408085,
    0.008015082,
    0.015147836,
    -0.021450333,
    -0.08121986,
    0.0066021825,
    -0.008981606,
    0.005120783,
    -0.046824142,
    0.05413864,
    -0.053240165,
    -0.0019565553,
    -0.040260732,
    -0.016520899,
    -0.035054557,
    0.008862485,
    -0.0063880286,
    0.05999729,
    0.022110062,
    0.019313497,
    -0.022694286,
    0.008775266,
    0.011965478,
    0.013934526,
    0.0643963,
    -0.014011274,
    -0.033534028,
    0.011058653,
    -0.0026869508,
    0.005486597,
    -0.018229062,
    -0.013453159,
    0.030076288,
    -0.07264647,
    -0.023085764,
    -0.0007928943,
    -0.048025016,
    0.01522257,
    0.025087992,
    -0.043548163,
    0.029908784,
    0.0011992821,
    -0.018729106,
    0.073118724,
    -0.038100295,
    -0.035207476,
    -0.0020452722,
    0.0028537253,
    -0.027142584,
    -0.006847706,
    0.0017353297,
    -0.03775611,
    -0.0071336445,
    -0.020442095,
    -0.058723982,
    -0.036656518,
    0.022570373,
    0.071906745,
    -0.025128074,
    -0.06896723,
    0.030328542,
    -0.037684422,
    0.022977145,
    0.0033660415,
    0.009622597,
    0.02708989,
    0.012317809,
    -0.0023158283,
    -0.03242781,
    0.04837669,
    -0.018706359,
    -0.021069434,
    0.018408228,
    -0.020975823,
    -0.05583589,
    -0.02022739,
    -0.0626174,
    0.008153623,
    -0.041393522,
    -0.035421297,
    -0.024023999,
    -0.057768974,
    -0.021249663,
    0.0069981986,
    0.052332725,
    -0.074382804,
    0.030754723,
    -0.0889937,
    -0.056282267,
    -0.05508031,
    0.077373356,
    -0.032565318,
    0.009482284,
    -0.0068523493,
    0.08500761,
    0.059892442,
    -0.030382782,
    -0.01002624,
    0.025064971,
    0.0033007942,
    -0.030008245,
    0.027475595,
    0.041410156,
    -0.0047356654,
    -0.012975197,
    0.052557226,
    0.079258464,
    0.05562695,
    0.014020671,
    0.0021802217,
    -0.015392949,
    0.03959488,
    0.0019404792,
    -0.09012611,
    -0.027630718,
    -0.002692745,
    -0.0366665,
    -0.018307848,
    0.0044481596,
    0.03904294,
    0.027376033,
    0.05390319,
    0.033562787,
    -0.09550131,
    -0.04779435,
    0.0061881724,
    0.02920162,
    -0.009856715,
    0.014616326,
    0.029402325,
    0.039996628,
    0.05160442,
    0.040374003,
    -0.015856221,
    -0.04388044,
    0.0308604,
    -0.006245484,
    0.048905406,
    0.029790035,
    -0.0127006555,
    -0.0927504,
    -0.00875912,
    -0.027050756,
    -0.035343386,
    -0.011272844,
    -0.0012634973,
    0.009162623,
    -0.009535692,
    0.003985182,
    -0.028485617,
    0.060744315,
    -0.038042255,
    -0.004667224,
    -0.0017726405,
    0.08838343,
    -0.0028684929,
    0.00792435,
    -0.007539089,
    -0.0013360165,
    0.0041064187,
    0.030455874,
    -0.03665891,
    -0.03201557,
    -0.014102733,
    -0.010245003,
    -0.021002524,
    0.0019153717,
    -0.029483737,
    0.028015835,
    0.0397581,
    0.010702673,
    0.014848801,
    0.017575048,
    0.016541641,
    0.013971351,
    0.018445369,
    -0.048541486,
    -0.047665156,
    0.032755267,
    0.04812482,
    -0.037164934,
    -0.014318755,
    -0.047513284,
    0.013143915,
    -0.0380336,
    -0.022192718,
    -0.026262984,
    -0.023735931,
    0.033247676,
    -0.052692905,
    -0.010871277,
    -0.022263497,
    -0.009835395,
    -0.07953543,
    -0.002389733,
    -0.03556975,
    -0.0014118702,
    -0.021818819,
    0.05527208,
    -0.0052123475,
    0.0020056409,
    -0.026969278,
    0.018715937,
    0.02460571,
    0.03129254,
    0.060154565,
    -0.02588996,
    -0.061426226,
    -0.019976797,
    -0.03323109,
    -0.009397253,
    -0.023147399,
    0.050081007,
    0.10129308,
    0.02537652,
    0.03051466,
    -0.007385527,
    0.024791809,
    0.024416165,
    -0.01695756,
    -0.048565324,
    -0.014661859,
    -0.016908033
  ],
  "metadata": {
    "source_file": "docs/rfcs/2026-03-03-adapter-plugin-system.md",
    "language": "markdown",
    "chunk_type": "heading_section",
    "start_line": 1916,
    "end_line": 1982,
    "content_role": "design",
    "source_origin": "repo:corvia"
  },
  "agent_id": null,
  "session_id": null,
  "entry_status": "Merged"
}